{"theory":"<p>Занятие 10. Множества\nЗадача «Кубики»</p>\n<p>Условие\nАня и Боря любят играть в разноцветные кубики, причем у каждого из них свой набор и в каждом наборе все кубики различны по цвету. Однажды дети заинтересовались, сколько существуют цветов таких, что кубики каждого цвета присутствуют в обоих наборах. Для этого они занумеровали все цвета случайными числами от 0 до 108. На этом их энтузиазм иссяк, поэтому вам предлагается помочь им в оставшейся части. В первой строке входных данных записаны числа N и M — число кубиков у Ани и Бори. В следующих N строках заданы номера цветов кубиков Ани. В последних M строках номера цветов Бори. Найдите три множества: номера цветов кубиков, которые есть в обоих наборах; номера цветов кубиков, которые есть только у Ани и номера цветов кубиков, которые есть только у Бори. Для каждого из множеств выведите сначала количество элементов в нем, а затем сами элементы, отсортированные по возрастанию.</p>\n<p>Во всех задачах считывайте входные данные через input() и выводите ответ через print().</p>\n<p>Примеры входных данных:</p>\n<pre><code>4 3\n0\n1\n10\n9\n1\n3\n0\n</code></pre>\n<p>Примеры выходных данных:</p>\n<pre><code>2\n0 1\n2\n9 10\n1\n3\n</code></pre>","meta":{"need_teacher_check":false,"globalTaskNum":104,"need_program_check":true,"task_type":"PT","chapterNum":10,"taskNum":5,"task_name":"Задача «Кубики»"},"test_data.txt":"_________________________\n4 3\n0\n1\n10\n9\n1\n3\n0\n=========================\n2\n0 1\n2\n9 10\n1\n3\n_________________________\n2 2\n1\n2\n2\n3\n=========================\n1\n2\n1\n1\n1\n3\n_________________________\n0 0\n=========================\n0\n\n0\n\n0\n_________________________\n1 1\n0\n1\n=========================\n0\n\n1\n0\n1\n1\n_________________________\n8 5\n1\n10\n100\n1000\n10000\n100000\n1000000\n10000000\n1\n100\n10000\n1000000\n100000000\n=========================\n4\n1\n100\n10000\n1000000\n4\n10\n1000\n100000\n10000000\n1\n100000000\n"}