{"meta":{"need_teacher_check":false,"task_type":"PT","chapterNum":5,"need_program_check":true,"globalTaskNum":48,"taskNum":1,"task_name":"Задача «Делаем срезы»"},"test_data.txt":"_________________________\nAbrakadabra\n=========================\nr\nr\nAbrak\nAbrakadab\nArkdba\nbaaar\narbadakarbA\nabdkrA\n11\n_________________________\nHello\n=========================\nl\nl\nHello\nHel\nHlo\nel\nolleH\nolH\n5\n_________________________\nqwertyuiop\n=========================\ne\no\nqwert\nqwertyui\nqetuo\nwryip\npoiuytrewq\npiyrw\n10\n_________________________\nasdfghjklzxcv\n=========================\nd\nc\nasdfg\nasdfghjklzx\nadgjlxv\nsfhkzc\nvcxzlkjhgfdsa\nvxljgda\n13\n","theory":"<p>Занятие 5. Строки\nЗадача «Делаем срезы»</p>\n<p>Условие\nДана строка.  Сначала выведите третий символ этой строки.  Во второй строке выведите предпоследний символ этой строки.  В третьей строке выведите первые пять символов этой строки.  В четвертой строке выведите всю строку, кроме последних двух символов.  В пятой строке выведите все символы с четными индексами (считая, что индексация начинается с 0, поэтому символы выводятся начиная с первого).  В шестой строке выведите все символы с нечетными индексами, то есть начиная со второго символа строки.  В седьмой строке выведите все символы в обратном порядке.  В восьмой строке выведите все символы строки через один в обратном порядке, начиная с последнего.  В девятой строке выведите длину данной строки.</p>\n<p>Во всех задачах считывайте входные данные через input() и выводите ответ через print().</p>\n<p>Примеры входных данных:</p>\n<pre><code>Abrakadabra\n</code></pre>\n<p>Примеры выходных данных:</p>\n<pre><code>r\nr\nAbrak\nAbrakadab\nArkdba\nbaaar\narbadakarbA\nabdkrA\n11\n</code></pre>"}